awslabs/__init__.py
awslabs/aws_network_mcp_server/__init__.py
awslabs/aws_network_mcp_server/server.py
awslabs/aws_network_mcp_server/tools/__init__.py
awslabs/aws_network_mcp_server/tools/cloud_wan/__init__.py
awslabs/aws_network_mcp_server/tools/cloud_wan/detect_cloudwan_inspection.py
awslabs/aws_network_mcp_server/tools/cloud_wan/get_all_cloudwan_routes.py
awslabs/aws_network_mcp_server/tools/cloud_wan/get_cloudwan_attachment_details.py
awslabs/aws_network_mcp_server/tools/cloud_wan/get_cloudwan_details.py
awslabs/aws_network_mcp_server/tools/cloud_wan/get_cloudwan_logs.py
awslabs/aws_network_mcp_server/tools/cloud_wan/get_cloudwan_peering_details.py
awslabs/aws_network_mcp_server/tools/cloud_wan/get_cloudwan_routes.py
awslabs/aws_network_mcp_server/tools/cloud_wan/list_cloudwan_peerings.py
awslabs/aws_network_mcp_server/tools/cloud_wan/list_core_networks.py
awslabs/aws_network_mcp_server/tools/cloud_wan/simulate_cloud_wan_route_change.py
awslabs/aws_network_mcp_server/tools/general/__init__.py
awslabs/aws_network_mcp_server/tools/general/find_ip_address.py
awslabs/aws_network_mcp_server/tools/general/get_eni_details.py
awslabs/aws_network_mcp_server/tools/general/get_path_trace_methodology.py
awslabs/aws_network_mcp_server/tools/network_firewall/__init__.py
awslabs/aws_network_mcp_server/tools/network_firewall/get_firewall_rules.py
awslabs/aws_network_mcp_server/tools/network_firewall/get_network_firewall_flow_logs.py
awslabs/aws_network_mcp_server/tools/network_firewall/list_network_firewalls.py
awslabs/aws_network_mcp_server/tools/transit_gateway/__init__.py
awslabs/aws_network_mcp_server/tools/transit_gateway/detect_transit_gateway_inspection.py
awslabs/aws_network_mcp_server/tools/transit_gateway/get_all_transit_gateway_routes.py
awslabs/aws_network_mcp_server/tools/transit_gateway/get_transit_gateway_details.py
awslabs/aws_network_mcp_server/tools/transit_gateway/get_transit_gateway_flow_logs.py
awslabs_aws_network_mcp_server-0.0.6.dist-info/METADATA
awslabs_aws_network_mcp_server-0.0.6.dist-info/WHEEL
awslabs_aws_network_mcp_server-0.0.6.dist-info/entry_points.txt
awslabs_aws_network_mcp_server-0.0.6.dist-info/licenses/LICENSE
awslabs_aws_network_mcp_server-0.0.6.dist-info/licenses/NOTICE
awslabs_aws_network_mcp_server-0.0.6.dist-info/RECORD
